MANIFEST.in
setup.cfg
setup.py
babigo/__init__.py
babigo/main.py
babigo.egg-info/PKG-INFO
babigo.egg-info/SOURCES.txt
babigo.egg-info/dependency_links.txt
babigo.egg-info/not-zip-safe
babigo.egg-info/requires.txt
babigo.egg-info/top_level.txt