Metadata-Version: 1.0
Name: babigo
Version: 0.1.1
Summary: babigo translate module
Home-page: https://github.com/yuokada/pythohn-babigo
Author: Yukihiro Okada
Author-email: callistoiv+pypi@gmail.com
License: BSD
Keywords: babigo nlp
Platform: UNKNOWN
Classifier: License :: OSI Approved :: BSD License
Classifier: Operating System :: OS Independent
Classifier: Programming Language :: Python :: 2.6
Classifier: Programming Language :: Python :: 2.7
